{
  "broendby": [
     {
      "id": 1,

      "img": "bif1.jpg"

      
    },
      
    
    
   
    
    {
      "id": 3,

      "img": "bif6.jpg"

    },
 
    
    {
      "id": 4,

      "img": "bif8.jpg"

      
    },
    {
      "id": 5,

      "img": "bif9.jpg"

    },
    {
      "id": 6,

      "img": "bif11.jpg"

    },
    {
      "id": 7,

      "img": "bif12.jpg"

    },
    {
      "id": 8,

      "img": "bif13.jpg"

    },
    {
      "id": 9,

      "img": "bif14.jpg"

    },
    {
      "id": 10,

      "img": "bif15.jpg"

    },
    {
      "id": 11,

      "img": "bif16.jpg"

    },
    {
      "id": 12,

      "img": "bif18.jpg"

    },
    {
      "id": 13,

      "img": "bif19.jpg"

    },
    {
      "id": 14,

      "img": "bif20.jpg"

    },
    {
      "id": 15,

      "img": "bif21.jpg"

    },
    {
      "id": 16,

      "img": "bif23.jpg"

    }
    
 
  ]
}